README.md
setup.cfg
setup.py
pi_1mp/__init__.py
pi_1mp.egg-info/PKG-INFO
pi_1mp.egg-info/SOURCES.txt
pi_1mp.egg-info/dependency_links.txt
pi_1mp.egg-info/not-zip-safe
pi_1mp.egg-info/top_level.txt